setup.py
udawsml_distrib/Binomialdistribution.py
udawsml_distrib/Gaussiandistribution.py
udawsml_distrib/Generaldistribution.py
udawsml_distrib/__init__.py
udawsml_distrib.egg-info/PKG-INFO
udawsml_distrib.egg-info/SOURCES.txt
udawsml_distrib.egg-info/dependency_links.txt
udawsml_distrib.egg-info/not-zip-safe
udawsml_distrib.egg-info/top_level.txt